atomcache/__init__.py
atomcache/backend.py
atomcache/base.py
atomcache/py.typed
atomcache/redis.py
atomcache-0.7.6.dist-info/LICENSE
atomcache-0.7.6.dist-info/METADATA
atomcache-0.7.6.dist-info/WHEEL
atomcache-0.7.6.dist-info/RECORD
