Metadata-Version: 2.1
Name: atomcache
Version: 0.7.6
Summary: Asynchronous cache manager designed for horizontally scaled web applications.
Home-page: https://github.com/pysergio/atomcache
License: MIT
Author: Serghei Ungurean
Author-email: srg@intelbit.io
Requires-Python: >=3.8,<4.0
Classifier: License :: OSI Approved :: MIT License
Classifier: Programming Language :: Python :: 3
Classifier: Programming Language :: Python :: 3.8
Classifier: Programming Language :: Python :: 3.9
Classifier: Programming Language :: Python :: 3.10
Classifier: Programming Language :: Python :: 3.11
Classifier: Programming Language :: Python :: 3.12
Requires-Dist: fastapi (>=0.61.2)
Requires-Dist: redis (>=4.5.4,<5.0.0)
Project-URL: Repository, https://github.com/pysergio/atomcache
